slurm_script_generator/main.py
slurm_script_generator/pragmas.py
slurm_script_generator/script.py
slurm_script_generator/slurm_script.py
slurm_script_generator/utils.py
slurm_script_generator-0.2.dist-info/METADATA
slurm_script_generator-0.2.dist-info/WHEEL
slurm_script_generator-0.2.dist-info/entry_points.txt
slurm_script_generator-0.2.dist-info/top_level.txt
slurm_script_generator-0.2.dist-info/RECORD
